{"cameraMode":{"drawMode":0,"name":"Shaded","section":"Shading Mode"},"sceneLighting":true,"audioPlay":false,"sceneViewState":{"m_AlwaysRefresh":false,"showFog":true,"showSkybox":true,"showFlares":true,"showImageEffects":true,"showParticleSystems":true,"showVisualEffectGraphs":true,"m_FxEnabled":true},"in2DMode":false,"pivot":{"x":0.6872792840003967,"y":1.9368358850479127,"z":-19.905014038085939},"rotation":{"x":-0.06589974462985993,"y":0.5372734069824219,"z":-0.04216521233320236,"w":-0.8398372530937195},"size":1.5389037132263184,"orthographic":false}